src/__init__.py
src/cli.py
src/core/__init__.py
src/core/config.py
src/core/processor.py
src/generator/__init__.py
src/generator/image_vector_generator.py
src/generator/template_engine.py
src/generator/templates/composable_function.j2
src/generator/templates/default.j2
src/generator/templates/icon_object.j2
src/generator/templates/val_declaration.j2
src/ir/__init__.py
src/ir/color.py
src/ir/gradient.py
src/ir/image_vector.py
src/ir/path_node.py
src/ir/svg_colors.py
src/ir/vector_node.py
src/parser/__init__.py
src/parser/gradient_parser.py
src/parser/path_parser.py
src/parser/svg_parser.py
src/parser/transform_parser.py
src/utils/__init__.py
src/utils/color_analyzer.py
src/utils/color_substitution.py
src/utils/formatting.py
src/utils/naming.py
svg_to_compose_vector-0.1.9.dist-info/METADATA
svg_to_compose_vector-0.1.9.dist-info/WHEEL
svg_to_compose_vector-0.1.9.dist-info/entry_points.txt
svg_to_compose_vector-0.1.9.dist-info/licenses/LICENSE
svg_to_compose_vector-0.1.9.dist-info/RECORD
