Metadata-Version: 2.4
Name: svg-to-compose-vector
Version: 0.1.9
Summary: Convert SVG files to Kotlin Compose ImageVector code with high fidelity and production-ready output
Project-URL: Homepage, https://github.com/chachako/svg-to-compose-vector
Project-URL: Repository, https://github.com/chachako/svg-to-compose-vector
Project-URL: Issues, https://github.com/chachako/svg-to-compose-vector/issues
Project-URL: Documentation, https://github.com/chachako/svg-to-compose-vector#readme
Author-email: Your Name <your.email@example.com>
Maintainer-email: Your Name <your.email@example.com>
License: MIT
License-File: LICENSE
Keywords: android,compose,conversion,graphics,imageVector,kotlin,svg,vector
Classifier: Development Status :: 4 - Beta
Classifier: Environment :: Console
Classifier: Intended Audience :: Developers
Classifier: License :: OSI Approved :: MIT License
Classifier: Operating System :: OS Independent
Classifier: Programming Language :: Python :: 3
Classifier: Programming Language :: Python :: 3.13
Classifier: Topic :: Multimedia :: Graphics :: Graphics Conversion
Classifier: Topic :: Software Development :: Code Generators
Classifier: Topic :: Software Development :: Libraries :: Python Modules
Requires-Python: >=3.13
Requires-Dist: click>=8.0.0
Requires-Dist: jinja2>=3.1.0
Requires-Dist: keyring>=25.6.0
